influenzanet/api/__init__.py
influenzanet/api/management_api.py
influenzanet/api/paginated.py
influenzanet/api/response_parser.py
influenzanet_api-1.3.1.dist-info/licenses/LICENCE
influenzanet_api-1.3.1.dist-info/METADATA
influenzanet_api-1.3.1.dist-info/WHEEL
influenzanet_api-1.3.1.dist-info/top_level.txt
influenzanet_api-1.3.1.dist-info/RECORD
